<?xml version='1.0' encoding='UTF-8'?>
<song xmlns="http://openlyrics.info/namespace/2009/song" version="0.8" createdIn="OpenLP 3.1.1" modifiedIn="OpenLP 3.1.1" modifiedDate="2024-04-11T13:59:25">
  <properties>
    <titles>
      <title>Aku Rindu pada-Mu Ya Tuhan</title>
    </titles>
    <authors>
      <author>Petrus somba</author>
    </authors>
  </properties>
  <lyrics>
    <verse name="v1a">
      <lines>Aku rindu pada-Mu ya Tuhan, aku rindu Tubuh Darah-Mu<br/>Hadirlah selalu ya Tuhan, tinggal dalam hati umat-Mu</lines>
    </verse>
    <verse name="v1b">
      <lines>Aku sungguh percaya Yesus-ku<br/>Kau hadir dalam Sakramen Mahakudus<br/>Aku ingin memeluk-Mu, persatukan diriku dengan-Mu<br/>Aku ingin memeluk-Mu, jangan biarkan 'ku terpisah dari-Mu.</lines>
    </verse>
    <verse name="v1c">
      <lines>Aku rindu pada-Mu ya Tuhan, aku rindu Tubuh Darah-Mu<br/>Hadirlah selalu ya Tuhan, tinggal dalam hati umat-Mu.</lines>
    </verse>
    <verse name="v1d">
      <lines>Aku sungguh merindukan Dikau<br/>saat tak dapat menyambut-Mu ya Yesus<br/>Maka datanglah ya Yesus, jiwaku rindukan Dikau Tuhan<br/>Aku ingin memeluk-Mu, jangan biarkan 'ku terpisah dari-Mu.</lines>
    </verse>
  </lyrics>
</song>
