<?xml version='1.0' encoding='UTF-8'?>
<song xmlns="http://openlyrics.info/namespace/2009/song" version="0.8" createdIn="OpenLP 3.1.1" modifiedIn="OpenLP 3.1.1" modifiedDate="2024-04-11T13:59:21">
  <properties>
    <titles>
      <title>PS 427 - Makanlah dan Minumnlah</title>
    </titles>
    <authors>
      <author>Aku kepunyaan-Mu Yesus</author>
    </authors>
  </properties>
  <lyrics>
    <verse name="v1a">
      <lines>Makanlah dan minumlah roti dari Tuhanmu: <br/>kenangan perjanjian baru.</lines>
    </verse>
    <verse name="v1b">
      <lines>Di dalam kecemasan Tuhan mendampingi; <br/>bila bersama makan perjamuan roti.</lines>
    </verse>
    <verse name="v1c">
      <lines>Pendosa pun diundang dalam pesta ini; <br/>agar kita bersama sehidup semati.</lines>
    </verse>
    <verse name="v1d">
      <lines>Tubuh-Nya diberikan menjadi makanan; <br/>Tuhan tumpuan iman kita tak'kan hilang.</lines>
    </verse>
    <verse name="v1e">
      <lines>Tuhan di tengah kita mewahyukan diri; <br/>sehingga manusia bersatu sehati.</lines>
    </verse>
    <verse name="v1f">
      <lines/>
    </verse>
  </lyrics>
</song>
