<?xml version='1.0' encoding='UTF-8'?>
<song xmlns="http://openlyrics.info/namespace/2009/song" version="0.8" createdIn="OpenLP 3.1.1" modifiedIn="OpenLP 3.1.1" modifiedDate="2024-04-11T13:59:18">
  <properties>
    <titles>
      <title>Yesus Kristus Tuhan</title>
    </titles>
    <authors>
      <author>JPCC</author>
    </authors>
  </properties>
  <lyrics>
    <verse name="v1a">
      <lines>Kupandang kemuliaanMu<br/>Imam Besar Maha Agung<br/>Kaulah pemilik hidupku<br/>Yesus Kristus Tuhan</lines>
    </verse>
    <verse name="v1b">
      <lines>Sujud di depan tahtaMu<br/>Taklukan s’luruh hidupku<br/>Dalam tanganMu penebus<br/>Yesus Kristus Tuhan</lines>
    </verse>
    <verse name="v1c">
      <lines>Tiada satupun yang luput<br/>Dari Karya kasihMu yang mulia<br/>BagiMu s’gala pujian<br/>Hormat kemuliaan</lines>
    </verse>
    <verse name="v1d">
      <lines>Engkau Tuhan kutinggikan<br/>Yang bangkit dan menang<br/>Yesus Kristus Tuhan<br/>Raja Mulia dan luhur<br/>Berkorban bagiku<br/>Slamatkan jiwaku</lines>
    </verse>
    <verse name="v1e">
      <lines>Maka jiwaku memuja<br/>Menyembah Sang Raja<br/>Yesus Kristus Tuhan<br/>Kekal sempurna kuasaMu<br/>Agunglah karyaMu<br/>Yesus Kristus Tuhan</lines>
    </verse>
    <verse name="v1f">
      <lines/>
    </verse>
  </lyrics>
</song>
